udm_rest_client/__init__.py
udm_rest_client/base.py
udm_rest_client/base_http.py
udm_rest_client/exceptions.py
udm_rest_client/udm.py
udm_rest_client-1.3.1.data/scripts/update_openapi_client
udm_rest_client-1.3.1.dist-info/LICENSE
udm_rest_client-1.3.1.dist-info/METADATA
udm_rest_client-1.3.1.dist-info/WHEEL
udm_rest_client-1.3.1.dist-info/top_level.txt
udm_rest_client-1.3.1.dist-info/RECORD
