Metadata-Version: 2.1
Name: udm-rest-client
Version: 1.3.1
Summary: Python library to interact with the Univention UDM REST API. Implements the simple Python UDM API.
Home-page: https://github.com/univention/python-udm-rest-api-client
Author: Daniel Troeder
Author-email: troeder@univention.de
License: GNU Affero General Public License v3
Keywords: Univention UCS UDM REST
Classifier: Development Status :: 4 - Beta
Classifier: Intended Audience :: Developers
Classifier: License :: OSI Approved :: GNU Affero General Public License v3
Classifier: Natural Language :: English
Classifier: Operating System :: OS Independent
Classifier: Programming Language :: Python :: 3.9
Classifier: Programming Language :: Python :: 3.10
Classifier: Programming Language :: Python :: 3.11
Classifier: Topic :: Software Development :: Libraries
Classifier: Topic :: System :: Systems Administration :: Authentication/Directory :: LDAP
Requires-Python: >=3.9
License-File: LICENSE
Requires-Dist: aiohttp<4,>=3.8.1
Requires-Dist: async-property<0.3,>=0.2.1
Requires-Dist: click<9,>=7
Requires-Dist: docker<8,>=7.1
Requires-Dist: requests<3,>=2.26
